pysimmmulator/VERSION
pysimmmulator/__init__.py
pysimmmulator/command_line.py
pysimmmulator/geos.py
pysimmmulator/load_parameters.py
pysimmmulator/param_handlers.py
pysimmmulator/simulate.py
pysimmmulator/study.py
pysimmmulator/visualize.py
pysimmmulator-0.5.0.dist-info/METADATA
pysimmmulator-0.5.0.dist-info/WHEEL
pysimmmulator-0.5.0.dist-info/entry_points.txt
pysimmmulator-0.5.0.dist-info/licenses/LICENSE
pysimmmulator-0.5.0.dist-info/RECORD
