Metadata-Version: 2.4
Name: pysimmmulator
Version: 0.5.0
Summary: Python package for generating MMM (Marketing Mix Model) input data
Author-email: Ryan Duecker <ryan.duecker@yahoo.com>
License: YEAR: 2024
License-File: LICENSE
Keywords: MMM,Marketing,Media,Model,SiMMMulator,Simulate
Classifier: License :: OSI Approved :: MIT License
Classifier: Operating System :: OS Independent
Classifier: Programming Language :: Python :: 3
Requires-Python: >=3.8
Requires-Dist: matplotlib
Requires-Dist: numpy
Requires-Dist: pandas
Requires-Dist: pyyaml
Provides-Extra: dev
Requires-Dist: black; extra == 'dev'
Requires-Dist: flake8; extra == 'dev'
Requires-Dist: pylint; extra == 'dev'
Requires-Dist: pytest; extra == 'dev'
Requires-Dist: sphinx; extra == 'dev'
Provides-Extra: docs
Requires-Dist: sphinx; extra == 'docs'
Provides-Extra: linting
Requires-Dist: flake8; extra == 'linting'
Requires-Dist: pylint; extra == 'linting'
Provides-Extra: testing
Requires-Dist: pytest; extra == 'testing'
